jxon/__init__.py
jxon/core.py
jxon_schema-0.2.0.dist-info/LICENSE
jxon_schema-0.2.0.dist-info/METADATA
jxon_schema-0.2.0.dist-info/WHEEL
jxon_schema-0.2.0.dist-info/top_level.txt
jxon_schema-0.2.0.dist-info/RECORD
