Metadata-Version: 2.2
Name: jxon-schema
Version: 0.2.0
Summary: JSON with change tracking - A library for converting between JSON and schemas with change tracking
Home-page: https://github.com/CoinEZ-JPN/lib_jxon
Author: Kenta Aratani
Author-email: Kenta Aratani <kenta.a.desu@gmail.com>
License: MIT
Project-URL: Homepage, https://github.com/CoinEZ-JPN/lib_jxon
Project-URL: Documentation, https://github.com/CoinEZ-JPN/lib_jxon#readme
Project-URL: Bug Tracker, https://github.com/CoinEZ-JPN/lib_jxon/issues
Project-URL: Source, https://github.com/CoinEZ-JPN/lib_jxon
Keywords: json,schema,openai,structured-data
Classifier: Development Status :: 4 - Beta
Classifier: Intended Audience :: Developers
Classifier: Programming Language :: Python :: 3
Classifier: Programming Language :: Python :: 3.8
Classifier: Programming Language :: Python :: 3.9
Classifier: Programming Language :: Python :: 3.10
Classifier: Programming Language :: Python :: 3.11
Classifier: Programming Language :: Python :: 3.12
Classifier: Programming Language :: Python :: 3.13
Classifier: License :: OSI Approved :: MIT License
Classifier: Operating System :: OS Independent
Classifier: Topic :: Software Development :: Libraries :: Python Modules
Classifier: Topic :: Utilities
Requires-Python: >=3.8
License-File: LICENSE
Requires-Dist: openai>=1.0.0
Provides-Extra: dev
Requires-Dist: pytest>=7.0.0; extra == "dev"
Requires-Dist: black>=23.0.0; extra == "dev"
Requires-Dist: mypy>=1.0.0; extra == "dev"
Dynamic: author
Dynamic: home-page
Dynamic: requires-python
